{"cameraMode":{"drawMode":0,"name":"Shaded","section":"Shading Mode"},"sceneLighting":true,"audioPlay":false,"sceneViewState":{"m_AlwaysRefresh":false,"showFog":true,"showSkybox":true,"showFlares":true,"showImageEffects":true,"showParticleSystems":true,"showVisualEffectGraphs":true,"m_FxEnabled":true},"in2DMode":false,"pivot":{"x":354.4841613769531,"y":215.6702423095703,"z":-325.5450134277344},"rotation":{"x":-0.05560312047600746,"y":-0.07964934408664704,"z":0.004465311765670776,"w":-0.9952900409698486},"size":0.7316936254501343,"orthographic":false}