{"cameraMode":{"drawMode":0,"name":"Shaded","section":"Shading Mode"},"sceneLighting":true,"audioPlay":false,"sceneViewState":{"m_AlwaysRefresh":false,"showFog":true,"showSkybox":true,"showFlares":true,"showImageEffects":true,"showParticleSystems":true,"showVisualEffectGraphs":true,"m_FxEnabled":true},"in2DMode":false,"pivot":{"x":-20.3648681640625,"y":1.0620478391647339,"z":-28.16303062438965},"rotation":{"x":0.2225629836320877,"y":0.6870227456092835,"z":0.23514223098754884,"w":-0.6506035327911377},"size":0.2868213653564453,"orthographic":false}